LICENSE
README.md
setup.cfg
setup.py
cloudmersive_image_api_client/__init__.py
cloudmersive_image_api_client/api_client.py
cloudmersive_image_api_client/configuration.py
cloudmersive_image_api_client/rest.py
cloudmersive_image_api_client.egg-info/PKG-INFO
cloudmersive_image_api_client.egg-info/SOURCES.txt
cloudmersive_image_api_client.egg-info/dependency_links.txt
cloudmersive_image_api_client.egg-info/requires.txt
cloudmersive_image_api_client.egg-info/top_level.txt
cloudmersive_image_api_client/api/__init__.py
cloudmersive_image_api_client/api/ai_image_detection_api.py
cloudmersive_image_api_client/api/artistic_api.py
cloudmersive_image_api_client/api/convert_api.py
cloudmersive_image_api_client/api/edit_api.py
cloudmersive_image_api_client/api/face_api.py
cloudmersive_image_api_client/api/filter_api.py
cloudmersive_image_api_client/api/info_api.py
cloudmersive_image_api_client/api/nsfw_api.py
cloudmersive_image_api_client/api/recognize_api.py
cloudmersive_image_api_client/api/resize_api.py
cloudmersive_image_api_client/api/text_generation_api.py
cloudmersive_image_api_client/models/__init__.py
cloudmersive_image_api_client/models/age_detection_result.py
cloudmersive_image_api_client/models/color_result.py
cloudmersive_image_api_client/models/create_handwriting_request.py
cloudmersive_image_api_client/models/detected_license_plate.py
cloudmersive_image_api_client/models/dominant_color_result.py
cloudmersive_image_api_client/models/draw_polygon_instance.py
cloudmersive_image_api_client/models/draw_polygon_request.py
cloudmersive_image_api_client/models/draw_rectangle_instance.py
cloudmersive_image_api_client/models/draw_rectangle_request.py
cloudmersive_image_api_client/models/draw_text_instance.py
cloudmersive_image_api_client/models/draw_text_request.py
cloudmersive_image_api_client/models/face.py
cloudmersive_image_api_client/models/face_compare_response.py
cloudmersive_image_api_client/models/face_locate_response.py
cloudmersive_image_api_client/models/face_locate_with_landmarks_response.py
cloudmersive_image_api_client/models/face_match.py
cloudmersive_image_api_client/models/face_point.py
cloudmersive_image_api_client/models/face_with_landmarks.py
cloudmersive_image_api_client/models/find_symbol_result.py
