Metadata-Version: 2.4
Name: cloudmersive_image_api_client
Version: 3.1.0
Summary: imageapi
Home-page: https://www.cloudmersive.com/image-recognition-and-processing-api
Author-email: 
Keywords: Swagger,imageapi
License-File: LICENSE
Requires-Dist: certifi>=2017.4.17
Requires-Dist: python-dateutil>=2.1
Requires-Dist: six>=1.10
Requires-Dist: urllib3>=1.23
Dynamic: description
Dynamic: description-content-type
Dynamic: home-page
Dynamic: keywords
Dynamic: license-file
Dynamic: requires-dist
Dynamic: summary
